mynb/__init__.py
mynb/main.py
mynb-0.0.2.dist-info/LICENSE
mynb-0.0.2.dist-info/METADATA
mynb-0.0.2.dist-info/WHEEL
mynb-0.0.2.dist-info/entry_points.txt
mynb-0.0.2.dist-info/top_level.txt
mynb-0.0.2.dist-info/RECORD
